pbiotools/__init__.py
pbiotools/misc/__init__.py
pbiotools/misc/logging_utils.py
pbiotools/misc/math_utils.py
pbiotools/misc/mpl_utils.py
pbiotools/misc/pandas_utils.py
pbiotools/misc/parallel.py
pbiotools/misc/shell_utils.py
pbiotools/misc/slurm.py
pbiotools/misc/suppress_stdout_stderr.py
pbiotools/misc/utils.py
pbiotools/utils/__init__.py
pbiotools/utils/bam_utils.py
pbiotools/utils/bed_utils.py
pbiotools/utils/bio.py
pbiotools/utils/fastx_utils.py
pbiotools/utils/gffread_utils.py
pbiotools/utils/gtf_utils.py
pbiotools/utils/meme_utils.py
pbiotools/utils/metacyc_utils.py
pbiotools/utils/mygene_utils.py
pbiotools/utils/pgrm_utils.py
pbiotools/utils/pgrms/__init__.py
pbiotools/utils/pgrms/add_mygene_info_to_orfs.py
pbiotools/utils/pgrms/bam_to_wiggle.py
pbiotools/utils/pgrms/bed12_to_gtf.py
pbiotools/utils/pgrms/bedx_to_bedy.py
pbiotools/utils/pgrms/convert_ccds_to_bed.py
pbiotools/utils/pgrms/count_aligned_reads.py
pbiotools/utils/pgrms/count_reads.py
pbiotools/utils/pgrms/create_mygene_report.py
pbiotools/utils/pgrms/dna_to_aa.py
pbiotools/utils/pgrms/download_srr_files.py
pbiotools/utils/pgrms/extract_bed_sequences.py
pbiotools/utils/pgrms/extract_cds_coordinates.py
pbiotools/utils/pgrms/fasta_to_fastq.py
pbiotools/utils/pgrms/fastq_pe_dedupe.py
pbiotools/utils/pgrms/filter_bam_by_ids.py
pbiotools/utils/pgrms/fix_all_bed_files.py
pbiotools/utils/pgrms/get_all_utrs.py
pbiotools/utils/pgrms/get_read_length_distribution.py
pbiotools/utils/pgrms/gtf_to_bed12.py
pbiotools/utils/pgrms/join_long_chromosomes.py
pbiotools/utils/pgrms/merge_isoforms.py
pbiotools/utils/pgrms/remove_duplicate_bed_entries.py
pbiotools/utils/pgrms/remove_duplicate_sequences.py
pbiotools/utils/pgrms/remove_multimapping_reads.py
pbiotools/utils/pgrms/reorder_fasta.py
pbiotools/utils/pgrms/run_bowtie.py
pbiotools/utils/pgrms/run_signalp.py
pbiotools/utils/pgrms/run_tmhmm.py
pbiotools/utils/pgrms/split_bed12_blocks.py
pbiotools/utils/pgrms/split_long_chromosomes.py
pbiotools-5.0.0.dist-info/licenses/LICENSE
pbiotools-5.0.0.dist-info/METADATA
pbiotools-5.0.0.dist-info/WHEEL
pbiotools-5.0.0.dist-info/entry_points.txt
pbiotools-5.0.0.dist-info/top_level.txt
pbiotools-5.0.0.dist-info/RECORD
