Metadata-Version: 2.4
Name: pbiotools
Version: 5.0.0
Summary: Miscellaneous bioinformatics and other supporting utilities for Python 3
Author: Brandon Malone
Maintainer-email: Etienne Boileau <boileau@uni-heidelberg.de>
License-Expression: MIT
Project-URL: Github, https://github.com/dieterich-lab/pbiotools
Project-URL: Issues, https://github.com/dieterich-lab/pbiotools/issues
Keywords: bioinformatics,riboseq
Classifier: Development Status :: 4 - Beta
Classifier: Intended Audience :: Science/Research
Classifier: Topic :: Scientific/Engineering :: Bio-Informatics
Classifier: Operating System :: MacOS :: MacOS X
Classifier: Operating System :: POSIX :: Linux
Classifier: Programming Language :: Python :: 3.11
Classifier: Programming Language :: Python :: 3.12
Classifier: Programming Language :: Python :: 3.13
Requires-Python: <3.14,>=3.11
License-File: LICENSE
Requires-Dist: biopython
Requires-Dist: joblib
Requires-Dist: matplotlib
Requires-Dist: mygene
Requires-Dist: numpy
Requires-Dist: pandas
Requires-Dist: pip
Requires-Dist: pysam
Requires-Dist: seaborn
Requires-Dist: scikit-learn
Requires-Dist: scipy
Requires-Dist: tqdm
Provides-Extra: tests
Requires-Dist: pytest; extra == "tests"
Requires-Dist: pytest-cov; extra == "tests"
Provides-Extra: docs
Requires-Dist: ipykernel; extra == "docs"
Requires-Dist: matplotlib; extra == "docs"
Requires-Dist: nbsphinx; extra == "docs"
Requires-Dist: pandoc; extra == "docs"
Requires-Dist: sphinx; extra == "docs"
Requires-Dist: sphinx_rtd_theme; extra == "docs"
Dynamic: license-file
